{"text": "Aerial shot of Arequipa view of the houses of a city with a few fields in the centre and a mountain range with a couple of snow covered peaks in the background; Arequipa, Peru images/02/2018.jpg ", "place": [{"id": "pl5", "new_text": "peaks", "new_start": 136, "new_end": 141}, {"id": "pl6", "new_text": "background", "new_start": 149, "new_end": 159}, {"id": "pl0", "new_text": "Arequipa", "new_start": 15, "new_end": 23}, {"id": "pl7", "new_text": "Arequipa, Peru", "new_start": 161, "new_end": 175}, {"id": "pl1", "new_text": "houses", "new_start": 36, "new_end": 42}, {"id": "pl2", "new_text": "city", "new_start": 48, "new_end": 52}, {"id": "pl3", "new_text": "fields", "new_start": 64, "new_end": 70}, {"id": "pl4", "new_text": "centre", "new_start": 78, "new_end": 84}], "path": [{"id": "p0", "new_text": "range", "new_start": 100, "new_end": 105}], "spatial_entity": [{"id": "se1", "new_text": "snow", "new_start": 123, "new_end": 127}], "nonmotion_event": [], "motion": [], "spatial_signal": [{"id": "s3", "new_text": "with", "new_start": 106, "new_end": 110}, {"id": "s4", "new_text": "covered", "new_start": 128, "new_end": 135}, {"id": "s0", "new_text": "of", "new_start": 43, "new_end": 45}, {"id": "s1", "new_text": "with", "new_start": 53, "new_end": 57}, {"id": "s2", "new_text": "in", "new_start": 71, "new_end": 73}], "motion_signal": [], "measure": [], "qslink": [], "olink": [], "movelink": []}